viewer3d/__init__.py
viewer3d/base.py
viewer3d/base3d.py
viewer3d/colors.py
viewer3d/config.py
viewer3d/converters.py
viewer3d/core.py
viewer3d/exceptions.py
viewer3d/initialization.py
viewer3d/modules.py
viewer3d/pose.py
viewer3d/presets.py
viewer3d/tracer.py
viewer3d/validators.py
viewer3d/widgets.py
viewer3d-1.0.0.dist-info/LICENSE
viewer3d-1.0.0.dist-info/METADATA
viewer3d-1.0.0.dist-info/WHEEL
viewer3d-1.0.0.dist-info/top_level.txt
viewer3d-1.0.0.dist-info/RECORD
