Metadata-Version: 2.1
Name: viewer3d
Version: 1.0.0
Summary: Display PackedPose objects, Pose objects, or PDB files within a Jupyter notebook and Google Colab.
Home-page: https://github.com/RosettaCommons/pyrosetta_viewer3d
Author: Jason C. Klima, Ajasja Ljubetic
License: MIT
License-File: LICENSE
Requires-Dist: attrs >=18.2.0
Requires-Dist: bokeh >=2.4.2
Requires-Dist: ipywidgets >=7.5.1
Requires-Dist: jupyter >=1.0.0
Requires-Dist: matplotlib >=3.5
Requires-Dist: py3Dmol >=1.8.0
